CTK_Color/__init__.py
ctk_color-0.0.2.dist-info/licenses/LICENSE
ctk_color-0.0.2.dist-info/METADATA
ctk_color-0.0.2.dist-info/WHEEL
ctk_color-0.0.2.dist-info/top_level.txt
ctk_color-0.0.2.dist-info/RECORD
