Metadata-Version: 2.4
Name: CTK_Color
Version: 0.0.2
Summary: A customizable color tool for CTkinter Textboxes
Home-page: https://github.com/vishal24102002/CTK_Color
Author: Vishal Sharma
Author-email: vishalsharma659615@gmail.com
License: MIT
Project-URL: Bug Tracker, https://github.com/vishal24102002/CTK_Color/issues
Project-URL: Documentation, https://github.com/vishal24102002/CTK_Color#readme
Project-URL: Source Code, https://github.com/vishal24102002/CTK_Color
Keywords: customtkinter ctkinter tkinter gui color textbox widget
Classifier: Development Status :: 3 - Alpha
Classifier: Intended Audience :: Developers
Classifier: Intended Audience :: Education
Classifier: Operating System :: OS Independent
Classifier: Topic :: Software Development :: Libraries :: Python Modules
Classifier: License :: OSI Approved :: MIT License
Requires-Python: >=3.7
License-File: LICENSE
Requires-Dist: customtkinter>=5.0.0
Dynamic: author
Dynamic: author-email
Dynamic: classifier
Dynamic: description
Dynamic: description-content-type
Dynamic: home-page
Dynamic: keywords
Dynamic: license
Dynamic: license-file
Dynamic: project-url
Dynamic: requires-dist
Dynamic: requires-python
Dynamic: summary
